setup.py
optionchain/__init__.py
optionchain/core.py
optionchain/utils.py
python_google_option_chain.egg-info/PKG-INFO
python_google_option_chain.egg-info/SOURCES.txt
python_google_option_chain.egg-info/dependency_links.txt
python_google_option_chain.egg-info/requires.txt
python_google_option_chain.egg-info/top_level.txt