Metadata-Version: 1.1
Name: python-google-option-chain
Version: 0.1
Summary: Python wrapper for getting data from Google's finance option chain
Home-page: https://github.com/makmac213/
Author: Mark Allan B Meriales
Author-email: mark.meriales@gmail.com
License: UNKNOWN
Download-URL: https://github.com/makmac213/python-google-option-chain
Platform: UNKNOWN
Classifier: Development Status :: 4 - Beta
Classifier: Intended Audience :: Developers
Classifier: Natural Language :: English
Classifier: Programming Language :: Python
Classifier: License :: Freeware
